VERSION
ez_setup.py
setup.py
django_renderform.egg-info/PKG-INFO
django_renderform.egg-info/SOURCES.txt
django_renderform.egg-info/dependency_links.txt
django_renderform.egg-info/not-zip-safe
django_renderform.egg-info/top_level.txt
renderform/__init__.py
renderform/models.py
renderform/tests.py
renderform/templates/forms/errors.html
renderform/templates/forms/field.html
renderform/templates/forms/form.html
renderform/templates/forms/help_text.html
renderform/templates/forms/label.html
renderform/templatetags/__init__.py
renderform/templatetags/forms.py