Metadata-Version: 1.0
Name: django-renderform
Version: 0.1
Summary: Helpers for rendering Django forms in a flexible way.
Home-page: http://code.google.com/p/django-renderform/
Author: Brian Beck
Author-email: exogen@gmail.com
License: MIT License
Platform: UNKNOWN
Classifier: Development Status :: 3 - Alpha
Classifier: Environment :: Web Environment
Classifier: Framework :: Django
Classifier: Intended Audience :: Developers
Classifier: License :: OSI Approved :: MIT License
Classifier: Topic :: Internet :: WWW/HTTP :: Dynamic Content
